[
 {
  "id": "lib-mini-w1-1",
  "kind": "mini",
  "title": "Warm-Up Lap",
  "author": "The Riddle Constructors",
  "difficulty": 1,
  "size": {
   "rows": 5,
   "cols": 5
  },
  "grid": [
   "##EYE",
   "PLEAD",
   "SORRY",
   "SPINS",
   "TEE##"
  ],
  "clues": {
   "across": [
    {
     "num": 1,
     "answer": "EYE",
     "clue": "Hurricane's calm middle",
     "stars": 3,
     "category": "science-nature",
     "tags": [
      "science",
      "nature"
     ]
    },
    {
     "num": 4,
     "answer": "PLEAD",
     "clue": "Ask on one's knees",
     "stars": 3,
     "category": "wordplay",
     "tags": [
      "sourced"
     ]
    },
    {
     "num": 6,
     "answer": "SORRY",
     "clue": "\"Pardon me\"",
     "stars": 3,
     "category": "wordplay",
     "register": "modern",
     "tags": [
      "sourced"
     ]
    },
    {
     "num": 7,
     "answer": "SPINS",
     "clue": "Plays a platter",
     "stars": 3,
     "category": "wordplay",
     "tags": [
      "sourced"
     ]
    },
    {
     "num": 8,
     "answer": "TEE",
     "clue": "Golfer's cheapest purchase",
     "stars": 3,
     "category": "wordplay",
     "tags": [
      "sourced"
     ]
    }
   ],
   "down": [
    {
     "num": 1,
     "answer": "EERIE",
     "clue": "Causing goose pimples",
     "stars": 3,
     "category": "wordplay",
     "tags": [
      "sourced"
     ]
    },
    {
     "num": 2,
     "answer": "YARN",
     "clue": "Sweater's raw material",
     "stars": 2,
     "category": "arts-literature",
     "register": "classic",
     "tags": [
      "books",
      "household"
     ]
    },
    {
     "num": 3,
     "answer": "EDYS",
     "clue": "\"Grand\" ice cream brand",
     "stars": 3,
     "category": "wordplay",
     "register": "modern",
     "tags": [
      "sourced"
     ]
    },
    {
     "num": 4,
     "answer": "PSST",
     "clue": "\"Check this out!\"",
     "stars": 3,
     "category": "wordplay",
     "register": "modern",
     "tags": [
      "sourced"
     ]
    },
    {
     "num": 5,
     "answer": "LOPE",
     "clue": "Easy, swinging gait",
     "stars": 3,
     "category": "wordplay",
     "tags": [
      "sourced"
     ]
    }
   ]
  },
  "weekday": 1
 },
 {
  "id": "lib-mini-w1-2",
  "kind": "mini",
  "title": "Gentle Start",
  "author": "The Riddle Constructors",
  "difficulty": 1,
  "size": {
   "rows": 5,
   "cols": 5
  },
  "grid": [
   "#RAE#",
   "EENSY",
   "VETTE",
   "ASSET",
   "#EYE#"
  ],
  "clues": {
   "across": [
    {
     "num": 1,
     "answer": "RAE",
     "clue": "Norma ___ (Sally Field role)",
     "stars": 3,
     "category": "entertainment",
     "tags": [
      "sourced"
     ]
    },
    {
     "num": 4,
     "answer": "EENSY",
     "clue": "'___-weensy' (super tiny)",
     "stars": 2,
     "category": "wordplay",
     "tags": [
      "handcraft"
     ]
    },
    {
     "num": 6,
     "answer": "VETTE",
     "clue": "Sporty Chevy, for short",
     "stars": 3,
     "category": "wordplay",
     "tags": [
      "sourced"
     ]
    },
    {
     "num": 7,
     "answer": "ASSET",
     "clue": "Money in the bank, say",
     "stars": 3,
     "category": "wordplay",
     "tags": [
      "sourced"
     ]
    },
    {
     "num": 8,
     "answer": "EYE",
     "clue": "Hurricane's calm middle",
     "stars": 3,
     "category": "science-nature",
     "tags": [
      "science",
      "nature"
     ]
    }
   ],
   "down": [
    {
     "num": 1,
     "answer": "REESE",
     "clue": "Witherspoon of \"Legally Blonde\"",
     "stars": 3,
     "category": "wordplay",
     "register": "modern",
     "tags": [
      "sourced"
     ]
    },
    {
     "num": 2,
     "answer": "ANTSY",
     "clue": "Unable to sit still",
     "stars": 3,
     "category": "wordplay",
     "tags": [
      "sourced"
     ]
    },
    {
     "num": 3,
     "answer": "ESTEE",
     "clue": "___ Lauder cosmetics",
     "stars": 3,
     "category": "wordplay",
     "tags": [
      "sourced"
     ]
    },
    {
     "num": 4,
     "answer": "EVA",
     "clue": "A Gabor sister",
     "stars": 3,
     "category": "wordplay",
     "tags": [
      "sourced"
     ]
    },
    {
     "num": 5,
     "answer": "YET",
     "clue": "\"Is it soup ___?\"",
     "stars": 3,
     "category": "wordplay",
     "register": "modern",
     "tags": [
      "sourced"
     ]
    }
   ]
  },
  "weekday": 1
 },
 {
  "id": "lib-mini-w1-3",
  "kind": "mini",
  "title": "First Sip",
  "author": "The Riddle Constructors",
  "difficulty": 1,
  "size": {
   "rows": 5,
   "cols": 5
  },
  "grid": [
   "NAH##",
   "OREOS",
   "NEATO",
   "EARTH",
   "##TOO"
  ],
  "clues": {
   "across": [
    {
     "num": 1,
     "answer": "NAH",
     "clue": "\"Count me out\"",
     "stars": 3,
     "category": "wordplay",
     "register": "modern",
     "tags": [
      "sourced"
     ]
    },
    {
     "num": 4,
     "answer": "OREOS",
     "clue": "Nabisco cookies",
     "stars": 2,
     "category": "wordplay",
     "tags": [
      "sourced"
     ]
    },
    {
     "num": 7,
     "answer": "NEATO",
     "clue": "\"Pretty amazing!\"",
     "stars": 3,
     "category": "wordplay",
     "register": "modern",
     "tags": [
      "sourced"
     ]
    },
    {
     "num": 8,
     "answer": "EARTH",
     "clue": "Third rock from the sun",
     "stars": 2,
     "category": "science-nature",
     "tags": [
      "science",
      "nature"
     ]
    },
    {
     "num": 9,
     "answer": "TOO",
     "clue": "'Me ___!' (agreement)",
     "stars": 2,
     "category": "wordplay",
     "tags": [
      "handcraft"
     ]
    }
   ],
   "down": [
    {
     "num": 1,
     "answer": "NONE",
     "clue": "___ of the above",
     "stars": 3,
     "category": "wordplay",
     "tags": [
      "sourced"
     ]
    },
    {
     "num": 2,
     "answer": "AREA",
     "clue": "Length times width, for a rectangle",
     "stars": 2,
     "category": "wordplay",
     "tags": [
      "school"
     ]
    },
    {
     "num": 3,
     "answer": "HEART",
     "clue": "Ticker in your chest",
     "stars": 3,
     "category": "science-nature",
     "tags": [
      "valentines",
      "science"
     ]
    },
    {
     "num": 5,
     "answer": "OTTO",
     "clue": "Palindromic boy's name",
     "stars": 1,
     "category": "history",
     "tags": [
      "history"
     ]
    },
    {
     "num": 6,
     "answer": "SOHO",
     "clue": "Big Apple neighborhood",
     "stars": 3,
     "category": "wordplay",
     "register": "modern",
     "tags": [
      "sourced"
     ]
    }
   ]
  },
  "weekday": 1
 },
 {
  "id": "lib-mini-w2-1",
  "kind": "mini",
  "title": "Second Gear",
  "author": "The Riddle Constructors",
  "difficulty": 2,
  "size": {
   "rows": 5,
   "cols": 5
  },
  "grid": [
   "ICE##",
   "CHEEP",
   "EARLE",
   "TRIAL",
   "##ENT"
  ],
  "clues": {
   "across": [
    {
     "num": 1,
     "answer": "ICE",
     "clue": "Cooler cubes",
     "stars": 2,
     "category": "science-nature",
     "tags": [
      "winter",
      "sports"
     ]
    },
    {
     "num": 4,
     "answer": "CHEEP",
     "clue": "Sound in a nest",
     "stars": 3,
     "category": "wordplay",
     "tags": [
      "sourced"
     ]
    },
    {
     "num": 7,
     "answer": "EARLE",
     "clue": "\"College Bowl\" host Robert",
     "stars": 3,
     "category": "wordplay",
     "register": "modern",
     "tags": [
      "sourced"
     ]
    },
    {
     "num": 8,
     "answer": "TRIAL",
     "clue": "Error's partner",
     "stars": 2,
     "category": "wordplay",
     "tags": [
      "sourced"
     ]
    },
    {
     "num": 9,
     "answer": "ENT",
     "clue": "A.F.B. in Colorado",
     "stars": 3,
     "category": "wordplay",
     "tags": [
      "sourced"
     ]
    }
   ],
   "down": [
    {
     "num": 1,
     "answer": "ICET",
     "clue": "\"Original Gangster\" rapper",
     "stars": 3,
     "category": "entertainment",
     "register": "modern",
     "tags": [
      "sourced"
     ]
    },
    {
     "num": 2,
     "answer": "CHAR",
     "clue": "Reduce to carbon",
     "stars": 3,
     "category": "wordplay",
     "tags": [
      "sourced"
     ]
    },
    {
     "num": 3,
     "answer": "EERIE",
     "clue": "Like a haunted house",
     "stars": 3,
     "category": "wordplay",
     "tags": [
      "sourced"
     ]
    },
    {
     "num": 5,
     "answer": "ELAN",
     "clue": "Spirited self-assurance",
     "stars": 2,
     "category": "wordplay",
     "tags": [
      "sourced"
     ]
    },
    {
     "num": 6,
     "answer": "PELT",
     "clue": "Trapper's prize",
     "stars": 1,
     "category": "history",
     "tags": [
      "history",
      "winter",
      "animals"
     ]
    }
   ]
  },
  "weekday": 2
 },
 {
  "id": "lib-mini-w2-2",
  "kind": "mini",
  "title": "Easy Does It",
  "author": "The Riddle Constructors",
  "difficulty": 2,
  "size": {
   "rows": 5,
   "cols": 5
  },
  "grid": [
   "#SIT#",
   "EERIE",
   "MEARA",
   "OTTER",
   "#OED#"
  ],
  "clues": {
   "across": [
    {
     "num": 1,
     "answer": "SIT",
     "clue": "Command to Rover",
     "stars": 3,
     "category": "wordplay",
     "tags": [
      "animals",
      "household"
     ]
    },
    {
     "num": 4,
     "answer": "EERIE",
     "clue": "Causing goose pimples",
     "stars": 3,
     "category": "wordplay",
     "tags": [
      "sourced"
     ]
    },
    {
     "num": 6,
     "answer": "MEARA",
     "clue": "Stiller's partner in comedy",
     "stars": 3,
     "category": "wordplay",
     "tags": [
      "sourced"
     ]
    },
    {
     "num": 7,
     "answer": "OTTER",
     "clue": "Playful stream swimmer",
     "stars": 1,
     "category": "science-nature",
     "tags": [
      "animals",
      "nature"
     ]
    },
    {
     "num": 8,
     "answer": "OED",
     "clue": "Brit. word reference",
     "stars": 3,
     "category": "wordplay",
     "tags": [
      "sourced"
     ]
    }
   ],
   "down": [
    {
     "num": 1,
     "answer": "SEETO",
     "clue": "Take care of, as duties",
     "stars": 3,
     "category": "wordplay",
     "tags": [
      "sourced"
     ]
    },
    {
     "num": 2,
     "answer": "IRATE",
     "clue": "Hopping mad",
     "stars": 2,
     "category": "wordplay",
     "tags": [
      "sourced"
     ]
    },
    {
     "num": 3,
     "answer": "TIRED",
     "clue": "All tuckered out",
     "stars": 3,
     "category": "wordplay",
     "tags": [
      "sourced"
     ]
    },
    {
     "num": 4,
     "answer": "EMO",
     "clue": "Punk rock subgenre",
     "stars": 3,
     "category": "wordplay",
     "tags": [
      "sourced"
     ]
    },
    {
     "num": 5,
     "answer": "EAR",
     "clue": "Corn unit",
     "stars": 2,
     "category": "science-nature",
     "tags": [
      "food",
      "music"
     ]
    }
   ]
  },
  "weekday": 2
 },
 {
  "id": "lib-mini-w2-3",
  "kind": "mini",
  "title": "Tuesday Trot",
  "author": "The Riddle Constructors",
  "difficulty": 2,
  "size": {
   "rows": 5,
   "cols": 5
  },
  "grid": [
   "ADO##",
   "RICES",
   "CREDO",
   "STAIR",
   "##NEE"
  ],
  "clues": {
   "across": [
    {
     "num": 1,
     "answer": "ADO",
     "clue": "Much ___ About Nothing",
     "stars": 2,
     "category": "arts-literature",
     "tags": [
      "books"
     ]
    },
    {
     "num": 4,
     "answer": "RICES",
     "clue": "Reduces to bits, as potatoes",
     "stars": 3,
     "category": "wordplay",
     "tags": [
      "sourced"
     ]
    },
    {
     "num": 7,
     "answer": "CREDO",
     "clue": "Words to live by",
     "stars": 3,
     "category": "wordplay",
     "tags": [
      "sourced"
     ]
    },
    {
     "num": 8,
     "answer": "STAIR",
     "clue": "Flight component",
     "stars": 3,
     "category": "wordplay",
     "tags": [
      "household"
     ]
    },
    {
     "num": 9,
     "answer": "NEE",
     "clue": "Barbara Bush, ___ Pierce",
     "stars": 3,
     "category": "wordplay",
     "tags": [
      "sourced"
     ]
    }
   ],
   "down": [
    {
     "num": 1,
     "answer": "ARCS",
     "clue": "Curved paths",
     "stars": 1,
     "category": "entertainment",
     "tags": [
      "movies"
     ]
    },
    {
     "num": 2,
     "answer": "DIRT",
     "clue": "Flowerbed filler",
     "stars": 1,
     "category": "wordplay",
     "tags": [
      "nature"
     ]
    },
    {
     "num": 3,
     "answer": "OCEAN",
     "clue": "Atlantic or Pacific",
     "stars": 1,
     "category": "geography",
     "tags": [
      "nature",
      "travel",
      "summer"
     ]
    },
    {
     "num": 5,
     "answer": "EDIE",
     "clue": "Falco of \"Nurse Jackie\"",
     "stars": 3,
     "category": "wordplay",
     "register": "modern",
     "tags": [
      "sourced"
     ]
    },
    {
     "num": 6,
     "answer": "SORE",
     "clue": "Like an ungracious loser",
     "stars": 3,
     "category": "wordplay",
     "tags": [
      "handcraft"
     ]
    }
   ]
  },
  "weekday": 2
 },
 {
  "id": "lib-mini-w3-1",
  "kind": "mini",
  "title": "Midweek Spark",
  "author": "The Riddle Constructors",
  "difficulty": 3,
  "size": {
   "rows": 5,
   "cols": 5
  },
  "grid": [
   "##EAT",
   "THANE",
   "AETNA",
   "TREES",
   "EON##"
  ],
  "clues": {
   "across": [
    {
     "num": 1,
     "answer": "EAT",
     "clue": "Absorb, as unexpected costs",
     "stars": 2,
     "category": "wordplay",
     "tags": [
      "food"
     ]
    },
    {
     "num": 4,
     "answer": "THANE",
     "clue": "___ of Cawdor",
     "stars": 3,
     "category": "wordplay",
     "tags": [
      "sourced"
     ]
    },
    {
     "num": 6,
     "answer": "AETNA",
     "clue": "Big name in insurance",
     "stars": 3,
     "category": "wordplay",
     "tags": [
      "sourced"
     ]
    },
    {
     "num": 7,
     "answer": "TREES",
     "clue": "They were all about Eve",
     "stars": 3,
     "category": "wordplay",
     "tags": [
      "sourced"
     ]
    },
    {
     "num": 8,
     "answer": "EON",
     "clue": "What a wait at the DMV feels like",
     "stars": 3,
     "category": "science-nature",
     "tags": [
      "time",
      "science"
     ]
    }
   ],
   "down": [
    {
     "num": 1,
     "answer": "EATEN",
     "clue": "Boccaccio's \"The ___ Heart\"",
     "stars": 4,
     "category": "wordplay",
     "register": "modern",
     "tags": [
      "sourced"
     ]
    },
    {
     "num": 2,
     "answer": "ANNE",
     "clue": "\"___ of the Thousand Days\"",
     "stars": 4,
     "category": "wordplay",
     "register": "modern",
     "tags": [
      "sourced"
     ]
    },
    {
     "num": 3,
     "answer": "TEAS",
     "clue": "Oolong and hyson",
     "stars": 3,
     "category": "wordplay",
     "tags": [
      "sourced"
     ]
    },
    {
     "num": 4,
     "answer": "TATE",
     "clue": "Where many Sargents hang, with \"the\"",
     "stars": 4,
     "category": "wordplay",
     "register": "modern",
     "tags": [
      "sourced"
     ]
    },
    {
     "num": 5,
     "answer": "HERO",
     "clue": "Sandwich that saves the day?",
     "stars": 4,
     "category": "arts-literature",
     "tags": [
      "books",
      "food",
      "movies"
     ]
    }
   ]
  },
  "weekday": 3
 },
 {
  "id": "lib-mini-w3-2",
  "kind": "mini",
  "title": "Hump Day Hustle",
  "author": "The Riddle Constructors",
  "difficulty": 3,
  "size": {
   "rows": 5,
   "cols": 5
  },
  "grid": [
   "##EAT",
   "PASTA",
   "EXTOL",
   "SEEME",
   "ODE##"
  ],
  "clues": {
   "across": [
    {
     "num": 1,
     "answer": "EAT",
     "clue": "Absorb, as unexpected costs",
     "stars": 2,
     "category": "wordplay",
     "tags": [
      "food"
     ]
    },
    {
     "num": 4,
     "answer": "PASTA",
     "clue": "Marathoner's mountain of carbs, the night before",
     "stars": 3,
     "category": "sports-leisure",
     "tags": [
      "food"
     ]
    },
    {
     "num": 6,
     "answer": "EXTOL",
     "clue": "Heap kudos on",
     "stars": 3,
     "category": "wordplay",
     "tags": [
      "sourced"
     ]
    },
    {
     "num": 7,
     "answer": "SEEME",
     "clue": "\"If My Friends Could ___ Now,\" 1966 song",
     "stars": 4,
     "category": "wordplay",
     "register": "modern",
     "tags": [
      "sourced"
     ]
    },
    {
     "num": 8,
     "answer": "ODE",
     "clue": "\"___ to Joy\"",
     "stars": 2,
     "category": "arts-literature",
     "tags": [
      "books",
      "music"
     ]
    }
   ],
   "down": [
    {
     "num": 1,
     "answer": "ESTEE",
     "clue": "___ Lauder cosmetics",
     "stars": 3,
     "category": "wordplay",
     "tags": [
      "sourced"
     ]
    },
    {
     "num": 2,
     "answer": "ATOM",
     "clue": "Splitting target for physicists",
     "stars": 2,
     "category": "science-nature",
     "tags": [
      "science",
      "school"
     ]
    },
    {
     "num": 3,
     "answer": "TALE",
     "clue": "Word after fairy or fish",
     "stars": 2,
     "category": "arts-literature",
     "tags": [
      "books"
     ]
    },
    {
     "num": 4,
     "answer": "PESO",
     "clue": "Currency south of the border",
     "stars": 2,
     "category": "geography",
     "tags": [
      "travel"
     ]
    },
    {
     "num": 5,
     "answer": "AXED",
     "clue": "Gave the boot",
     "stars": 3,
     "category": "wordplay",
     "tags": [
      "sourced"
     ]
    }
   ]
  },
  "weekday": 3
 },
 {
  "id": "lib-mini-w3-3",
  "kind": "mini",
  "title": "Wednesday Wink",
  "author": "The Riddle Constructors",
  "difficulty": 3,
  "size": {
   "rows": 5,
   "cols": 5
  },
  "grid": [
   "PIE##",
   "ASSES",
   "LETME",
   "SEEME",
   "##EAR"
  ],
  "clues": {
   "across": [
    {
     "num": 1,
     "answer": "PIE",
     "clue": "Chart with slices",
     "stars": 3,
     "category": "sports-leisure",
     "tags": [
      "food",
      "thanksgiving"
     ]
    },
    {
     "num": 4,
     "answer": "ASSES",
     "clue": "Beasts of burden",
     "stars": 3,
     "category": "wordplay",
     "tags": [
      "sourced"
     ]
    },
    {
     "num": 7,
     "answer": "LETME",
     "clue": "\"___ Entertain You\"",
     "stars": 4,
     "category": "wordplay",
     "register": "modern",
     "tags": [
      "sourced"
     ]
    },
    {
     "num": 8,
     "answer": "SEEME",
     "clue": "\"Come up and ___ sometime\"",
     "stars": 4,
     "category": "wordplay",
     "register": "modern",
     "tags": [
      "sourced"
     ]
    },
    {
     "num": 9,
     "answer": "EAR",
     "clue": "What a natural musician plays by",
     "stars": 3,
     "category": "science-nature",
     "tags": [
      "food",
      "music"
     ]
    }
   ],
   "down": [
    {
     "num": 1,
     "answer": "PALS",
     "clue": "Gleason and Carney on TV",
     "stars": 3,
     "category": "wordplay",
     "tags": [
      "sourced"
     ]
    },
    {
     "num": 2,
     "answer": "ISEE",
     "clue": "What \"video\" means",
     "stars": 4,
     "category": "wordplay",
     "register": "modern",
     "tags": [
      "sourced"
     ]
    },
    {
     "num": 3,
     "answer": "ESTEE",
     "clue": "First name in skin care",
     "stars": 3,
     "category": "wordplay",
     "tags": [
      "sourced"
     ]
    },
    {
     "num": 5,
     "answer": "EMMA",
     "clue": "Novel on which \"Clueless\" is based",
     "stars": 4,
     "category": "arts-literature",
     "register": "modern",
     "tags": [
      "sourced"
     ]
    },
    {
     "num": 6,
     "answer": "SEER",
     "clue": "Melampus was one",
     "stars": 3,
     "category": "wordplay",
     "tags": [
      "sourced"
     ]
    }
   ]
  },
  "weekday": 3
 },
 {
  "id": "lib-mini-w4-1",
  "kind": "mini",
  "title": "Thursday Twist",
  "author": "The Riddle Constructors",
  "difficulty": 4,
  "size": {
   "rows": 5,
   "cols": 5
  },
  "grid": [
   "#GRO#",
   "DEUCE",
   "YENTA",
   "ESTER",
   "#EST#"
  ],
  "clues": {
   "across": [
    {
     "num": 1,
     "answer": "GRO",
     "clue": "_____ Harlem Brudtland (Norwegian leader)",
     "stars": 3,
     "category": "wordplay",
     "tags": [
      "sourced"
     ]
    },
    {
     "num": 4,
     "answer": "DEUCE",
     "clue": "What turns 19 into 21?",
     "stars": 5,
     "category": "wordplay",
     "tags": [
      "sourced"
     ]
    },
    {
     "num": 6,
     "answer": "YENTA",
     "clue": "\"Fiddler on the Roof\" role",
     "stars": 4,
     "category": "wordplay",
     "register": "modern",
     "tags": [
      "sourced"
     ]
    },
    {
     "num": 7,
     "answer": "ESTER",
     "clue": "Ethyl acetate, e.g.",
     "stars": 3,
     "category": "wordplay",
     "tags": [
      "sourced"
     ]
    },
    {
     "num": 8,
     "answer": "EST",
     "clue": "Winter hrs. in Boston",
     "stars": 1,
     "category": "geography",
     "tags": [
      "travel",
      "winter"
     ]
    }
   ],
   "down": [
    {
     "num": 1,
     "answer": "GEESE",
     "clue": "Fliers in V's",
     "stars": 3,
     "category": "wordplay",
     "tags": [
      "sourced"
     ]
    },
    {
     "num": 2,
     "answer": "RUNTS",
     "clue": "Littlest ones in litters",
     "stars": 3,
     "category": "wordplay",
     "tags": [
      "sourced"
     ]
    },
    {
     "num": 3,
     "answer": "OCTET",
     "clue": "Wedding band, maybe",
     "stars": 3,
     "category": "wordplay",
     "tags": [
      "sourced"
     ]
    },
    {
     "num": 4,
     "answer": "DYE",
     "clue": "Salon bottle's transformer",
     "stars": 2,
     "category": "science-nature",
     "tags": [
      "art",
      "household"
     ]
    },
    {
     "num": 5,
     "answer": "EAR",
     "clue": "What a natural musician plays by",
     "stars": 3,
     "category": "science-nature",
     "tags": [
      "food",
      "music"
     ]
    }
   ]
  },
  "weekday": 4
 },
 {
  "id": "lib-mini-w4-2",
  "kind": "mini",
  "title": "Almost Friday",
  "author": "The Riddle Constructors",
  "difficulty": 4,
  "size": {
   "rows": 5,
   "cols": 5
  },
  "grid": [
   "ISH##",
   "ONEPM",
   "TIARA",
   "APRON",
   "##TMI"
  ],
  "clues": {
   "across": [
    {
     "num": 1,
     "answer": "ISH",
     "clue": "Relative of -esque",
     "stars": 3,
     "category": "wordplay",
     "tags": [
      "sourced"
     ]
    },
    {
     "num": 4,
     "answer": "ONEPM",
     "clue": "When lunch ends, maybe",
     "stars": 4,
     "category": "wordplay",
     "tags": [
      "sourced"
     ]
    },
    {
     "num": 7,
     "answer": "TIARA",
     "clue": "Miss America topper",
     "stars": 3,
     "category": "wordplay",
     "tags": [
      "sourced"
     ]
    },
    {
     "num": 8,
     "answer": "APRON",
     "clue": "Stage's forward edge",
     "stars": 3,
     "category": "wordplay",
     "tags": [
      "food",
      "household"
     ]
    },
    {
     "num": 9,
     "answer": "TMI",
     "clue": "\"Eww, I don't want to hear about it,\" in a text",
     "stars": 4,
     "category": "wordplay",
     "register": "modern",
     "tags": [
      "sourced"
     ]
    }
   ],
   "down": [
    {
     "num": 1,
     "answer": "IOTA",
     "clue": "Between theta and kappa",
     "stars": 3,
     "category": "wordplay",
     "register": "modern",
     "tags": [
      "sourced"
     ]
    },
    {
     "num": 2,
     "answer": "SNIP",
     "clue": "Short, quick cut",
     "stars": 3,
     "category": "wordplay",
     "tags": [
      "sourced"
     ]
    },
    {
     "num": 3,
     "answer": "HEART",
     "clue": "It skips a beat, in romances",
     "stars": 3,
     "category": "science-nature",
     "tags": [
      "valentines",
      "science"
     ]
    },
    {
     "num": 5,
     "answer": "PROM",
     "clue": "Corsage occasion",
     "stars": 2,
     "category": "entertainment",
     "tags": [
      "spring",
      "school",
      "music"
     ]
    },
    {
     "num": 6,
     "answer": "MANI",
     "clue": "Gershwin's \"The ___ Love\": 1924",
     "stars": 4,
     "category": "wordplay",
     "register": "modern",
     "tags": [
      "sourced"
     ]
    }
   ]
  },
  "weekday": 4
 },
 {
  "id": "lib-mini-w4-3",
  "kind": "mini",
  "title": "The Long Bridge",
  "author": "The Riddle Constructors",
  "difficulty": 4,
  "size": {
   "rows": 5,
   "cols": 5
  },
  "grid": [
   "#TMI#",
   "FEINT",
   "INANE",
   "ESTEE",
   "#EAR#"
  ],
  "clues": {
   "across": [
    {
     "num": 1,
     "answer": "TMI",
     "clue": "\"Eww, I don't want to hear about it,\" in a text",
     "stars": 4,
     "category": "wordplay",
     "register": "modern",
     "tags": [
      "sourced"
     ]
    },
    {
     "num": 4,
     "answer": "FEINT",
     "clue": "Ruse in the ring",
     "stars": 3,
     "category": "wordplay",
     "tags": [
      "sourced"
     ]
    },
    {
     "num": 6,
     "answer": "INANE",
     "clue": "Pointless",
     "stars": 2,
     "category": "wordplay",
     "tags": [
      "sourced"
     ]
    },
    {
     "num": 7,
     "answer": "ESTEE",
     "clue": "First name in skin care",
     "stars": 3,
     "category": "wordplay",
     "tags": [
      "sourced"
     ]
    },
    {
     "num": 8,
     "answer": "EAR",
     "clue": "What a natural musician plays by",
     "stars": 3,
     "category": "science-nature",
     "tags": [
      "food",
      "music"
     ]
    }
   ],
   "down": [
    {
     "num": 1,
     "answer": "TENSE",
     "clue": "Past or present",
     "stars": 3,
     "category": "wordplay",
     "tags": [
      "sourced"
     ]
    },
    {
     "num": 2,
     "answer": "MIATA",
     "clue": "Popular sports car",
     "stars": 3,
     "category": "wordplay",
     "tags": [
      "sourced"
     ]
    },
    {
     "num": 3,
     "answer": "INNER",
     "clue": "___ peace",
     "stars": 1,
     "category": "wordplay"
    },
    {
     "num": 4,
     "answer": "FIE",
     "clue": "\"For shame!\"",
     "stars": 3,
     "category": "wordplay",
     "register": "modern",
     "tags": [
      "sourced"
     ]
    },
    {
     "num": 5,
     "answer": "TEE",
     "clue": "Start of a hole",
     "stars": 3,
     "category": "wordplay",
     "tags": [
      "sourced"
     ]
    }
   ]
  },
  "weekday": 4
 },
 {
  "id": "lib-mini-w5-1",
  "kind": "mini",
  "title": "Friday Flourish",
  "author": "The Riddle Constructors",
  "difficulty": 5,
  "size": {
   "rows": 5,
   "cols": 5
  },
  "grid": [
   "##HEE",
   "TIEIN",
   "AWARD",
   "MARES",
   "EST##"
  ],
  "clues": {
   "across": [
    {
     "num": 1,
     "answer": "HEE",
     "clue": "TV's \"___ Haw\"",
     "stars": 4,
     "category": "entertainment",
     "register": "modern",
     "tags": [
      "sourced"
     ]
    },
    {
     "num": 4,
     "answer": "TIEIN",
     "clue": "Soundtrack album, e.g.",
     "stars": 3,
     "category": "wordplay",
     "tags": [
      "sourced"
     ]
    },
    {
     "num": 6,
     "answer": "AWARD",
     "clue": "Trophy or ribbon",
     "stars": 1,
     "category": "entertainment",
     "tags": [
      "fill"
     ]
    },
    {
     "num": 7,
     "answer": "MARES",
     "clue": "Kind of nest",
     "stars": 3,
     "category": "wordplay",
     "tags": [
      "sourced"
     ]
    },
    {
     "num": 8,
     "answer": "EST",
     "clue": "Winter hrs. in Boston",
     "stars": 1,
     "category": "geography",
     "tags": [
      "travel",
      "winter"
     ]
    }
   ],
   "down": [
    {
     "num": 1,
     "answer": "HEART",
     "clue": "It skips a beat, in romances",
     "stars": 3,
     "category": "science-nature",
     "tags": [
      "valentines",
      "science"
     ]
    },
    {
     "num": 2,
     "answer": "EIRE",
     "clue": "Where Hyde once presided",
     "stars": 3,
     "category": "wordplay",
     "tags": [
      "sourced"
     ]
    },
    {
     "num": 3,
     "answer": "ENDS",
     "clue": "They supposedly justify the means",
     "stars": 2,
     "category": "wordplay"
    },
    {
     "num": 4,
     "answer": "TAME",
     "clue": "Mild, as a thrill ride",
     "stars": 2,
     "category": "science-nature",
     "tags": [
      "animals"
     ]
    },
    {
     "num": 5,
     "answer": "IWAS",
     "clue": "\"___ a King in Babylon\": Henley",
     "stars": 4,
     "category": "entertainment",
     "register": "modern",
     "tags": [
      "sourced"
     ]
    }
   ]
  },
  "weekday": 5
 },
 {
  "id": "lib-mini-w5-2",
  "kind": "mini",
  "title": "Weekend Warm-Up",
  "author": "The Riddle Constructors",
  "difficulty": 5,
  "size": {
   "rows": 5,
   "cols": 5
  },
  "grid": [
   "ATE##",
   "TREES",
   "TORTE",
   "ANITA",
   "##EAT"
  ],
  "clues": {
   "across": [
    {
     "num": 1,
     "answer": "ATE",
     "clue": "Polished off a plate",
     "stars": 2,
     "category": "wordplay",
     "tags": [
      "food"
     ]
    },
    {
     "num": 4,
     "answer": "TREES",
     "clue": "Last of a Hemingway title",
     "stars": 3,
     "category": "wordplay",
     "tags": [
      "sourced"
     ]
    },
    {
     "num": 7,
     "answer": "TORTE",
     "clue": "Sacher ___ (a pastry)",
     "stars": 3,
     "category": "wordplay",
     "tags": [
      "sourced"
     ]
    },
    {
     "num": 8,
     "answer": "ANITA",
     "clue": "\"The Red Tent\" author Diamant",
     "stars": 4,
     "category": "sports-leisure",
     "register": "modern",
     "tags": [
      "sourced"
     ]
    },
    {
     "num": 9,
     "answer": "EAT",
     "clue": "Absorb, as unexpected costs",
     "stars": 2,
     "category": "wordplay",
     "tags": [
      "food"
     ]
    }
   ],
   "down": [
    {
     "num": 1,
     "answer": "ATTA",
     "clue": "Heine's \"___ Troll\"",
     "stars": 4,
     "category": "wordplay",
     "register": "modern",
     "tags": [
      "sourced"
     ]
    },
    {
     "num": 2,
     "answer": "TRON",
     "clue": "Word form meaning \"vacuum tube\"",
     "stars": 4,
     "category": "entertainment",
     "register": "modern",
     "tags": [
      "sourced"
     ]
    },
    {
     "num": 3,
     "answer": "EERIE",
     "clue": "Like a haunted house",
     "stars": 3,
     "category": "wordplay",
     "tags": [
      "sourced"
     ]
    },
    {
     "num": 5,
     "answer": "ETTA",
     "clue": "Kett of comics",
     "stars": 3,
     "category": "wordplay",
     "tags": [
      "sourced"
     ]
    },
    {
     "num": 6,
     "answer": "SEAT",
     "clue": "It's often taken but never stolen?",
     "stars": 4,
     "category": "wordplay",
     "tags": [
      "travel"
     ]
    }
   ]
  },
  "weekday": 5
 },
 {
  "id": "lib-mini-w5-3",
  "kind": "mini",
  "title": "Five O’Clock Somewhere",
  "author": "The Riddle Constructors",
  "difficulty": 5,
  "size": {
   "rows": 5,
   "cols": 5
  },
  "grid": [
   "EWE##",
   "TEMPO",
   "TROOP",
   "AETNA",
   "##EEL"
  ],
  "clues": {
   "across": [
    {
     "num": 1,
     "answer": "EWE",
     "clue": "Flock mother",
     "stars": 2,
     "category": "science-nature",
     "tags": [
      "animals",
      "nature"
     ]
    },
    {
     "num": 4,
     "answer": "TEMPO",
     "clue": "It picks up in an accelerando",
     "stars": 3,
     "category": "entertainment",
     "tags": [
      "music"
     ]
    },
    {
     "num": 7,
     "answer": "TROOP",
     "clue": "Group of Boy Scouts",
     "stars": 3,
     "category": "wordplay",
     "tags": [
      "sourced"
     ]
    },
    {
     "num": 8,
     "answer": "AETNA",
     "clue": "Where Vulcan forged",
     "stars": 3,
     "category": "wordplay",
     "tags": [
      "sourced"
     ]
    },
    {
     "num": 9,
     "answer": "EEL",
     "clue": "Unagi, at a sushi bar",
     "stars": 2,
     "category": "science-nature",
     "tags": [
      "animals",
      "food"
     ]
    }
   ],
   "down": [
    {
     "num": 1,
     "answer": "ETTA",
     "clue": "\"At Last\" singer James",
     "stars": 3,
     "category": "wordplay",
     "register": "modern",
     "tags": [
      "sourced"
     ]
    },
    {
     "num": 2,
     "answer": "WERE",
     "clue": "\"You ___ Made for Me\"",
     "stars": 4,
     "category": "wordplay",
     "register": "modern",
     "tags": [
      "sourced"
     ]
    },
    {
     "num": 3,
     "answer": "EMOTE",
     "clue": "Act badly?",
     "stars": 4,
     "category": "wordplay",
     "tags": [
      "sourced"
     ]
    },
    {
     "num": 5,
     "answer": "PONE",
     "clue": "Southern side?",
     "stars": 4,
     "category": "wordplay",
     "tags": [
      "sourced"
     ]
    },
    {
     "num": 6,
     "answer": "OPAL",
     "clue": "Gem with fire but no flame?",
     "stars": 4,
     "category": "science-nature",
     "tags": [
      "nature",
      "art"
     ]
    }
   ]
  },
  "weekday": 5
 },
 {
  "id": "lib-mini-w6-1",
  "kind": "mini",
  "title": "Saturday Stinger",
  "author": "The Riddle Constructors",
  "difficulty": 6,
  "size": {
   "rows": 7,
   "cols": 7
  },
  "grid": [
   "ONE#LIP",
   "RES#ERA",
   "ESTATES",
   "##HOT##",
   "SEEKERS",
   "PAT#ROO",
   "ATE#STY"
  ],
  "clues": {
   "across": [
    {
     "num": 1,
     "answer": "ONE",
     "clue": "Bill in a tip jar",
     "stars": 2,
     "category": "wordplay"
    },
    {
     "num": 4,
     "answer": "LIP",
     "clue": "Back talk",
     "stars": 3,
     "category": "wordplay"
    },
    {
     "num": 7,
     "answer": "RES",
     "clue": "In medias ___",
     "stars": 3,
     "category": "wordplay",
     "tags": [
      "sourced"
     ]
    },
    {
     "num": 8,
     "answer": "ERA",
     "clue": "Jazz Age or Space Age, e.g.",
     "stars": 2,
     "category": "history",
     "tags": [
      "time",
      "history"
     ]
    },
    {
     "num": 9,
     "answer": "ESTATES",
     "clue": "They're left behind",
     "stars": 3,
     "category": "wordplay",
     "tags": [
      "sourced"
     ]
    },
    {
     "num": 11,
     "answer": "HOT",
     "clue": "In high demand",
     "stars": 2,
     "category": "science-nature",
     "tags": [
      "summer",
      "food"
     ]
    },
    {
     "num": 12,
     "answer": "SEEKERS",
     "clue": "They're on hunts",
     "stars": 3,
     "category": "wordplay",
     "tags": [
      "sourced"
     ]
    },
    {
     "num": 16,
     "answer": "PAT",
     "clue": "Butter portion",
     "stars": 1,
     "category": "wordplay",
     "tags": [
      "food"
     ]
    },
    {
     "num": 17,
     "answer": "ROO",
     "clue": "Aussie hopper, for short",
     "stars": 3,
     "category": "wordplay",
     "tags": [
      "sourced"
     ]
    },
    {
     "num": 18,
     "answer": "ATE",
     "clue": "Polished off a plate",
     "stars": 2,
     "category": "wordplay",
     "tags": [
      "food"
     ]
    },
    {
     "num": 19,
     "answer": "STY",
     "clue": "Pork place?",
     "stars": 4,
     "category": "wordplay",
     "tags": [
      "sourced"
     ]
    }
   ],
   "down": [
    {
     "num": 1,
     "answer": "ORE",
     "clue": "Rock with metal hiding inside",
     "stars": 2,
     "category": "science-nature",
     "tags": [
      "nature",
      "science"
     ]
    },
    {
     "num": 2,
     "answer": "NES",
     "clue": "Super ___ (video game name)",
     "stars": 3,
     "category": "sports-leisure",
     "tags": [
      "sourced"
     ]
    },
    {
     "num": 3,
     "answer": "ESTHETE",
     "clue": "Cultivator of beauty",
     "stars": 3,
     "category": "wordplay",
     "tags": [
      "sourced"
     ]
    },
    {
     "num": 4,
     "answer": "LETTERS",
     "clue": "Scrabble tiles' cargo",
     "stars": 1,
     "category": "arts-literature",
     "tags": [
      "fill",
      "games",
      "school"
     ]
    },
    {
     "num": 5,
     "answer": "IRE",
     "clue": "What a hothead runs hot with",
     "stars": 2,
     "category": "wordplay",
     "tags": [
      "books"
     ]
    },
    {
     "num": 6,
     "answer": "PAS",
     "clue": "Ballerina's ___ seul",
     "stars": 3,
     "category": "wordplay",
     "tags": [
      "sourced"
     ]
    },
    {
     "num": 10,
     "answer": "AOK",
     "clue": "Astronaut's \"All systems go\"",
     "stars": 3,
     "category": "wordplay",
     "register": "modern",
     "tags": [
      "sourced"
     ]
    },
    {
     "num": 12,
     "answer": "SPA",
     "clue": "Resort with robes and cucumber water",
     "stars": 2,
     "category": "sports-leisure",
     "tags": [
      "travel"
     ]
    },
    {
     "num": 13,
     "answer": "EAT",
     "clue": "Absorb, as unexpected costs",
     "stars": 2,
     "category": "wordplay",
     "tags": [
      "food"
     ]
    },
    {
     "num": 14,
     "answer": "ROT",
     "clue": "Nonsense, to a Brit",
     "stars": 2,
     "category": "science-nature",
     "tags": [
      "nature"
     ]
    },
    {
     "num": 15,
     "answer": "SOY",
     "clue": "Kind of sauce",
     "stars": 3,
     "category": "wordplay",
     "tags": [
      "sourced"
     ]
    }
   ]
  },
  "weekday": 6
 },
 {
  "id": "lib-mini-w6-2",
  "kind": "mini",
  "title": "The Deep End",
  "author": "The Riddle Constructors",
  "difficulty": 6,
  "size": {
   "rows": 7,
   "cols": 7
  },
  "grid": [
   "REN#THE",
   "TEA#AIR",
   "ELNORTE",
   "##EAT##",
   "RATTAIL",
   "OPT#RAE",
   "NEE#ENT"
  ],
  "clues": {
   "across": [
    {
     "num": 1,
     "answer": "REN",
     "clue": "Nickelodeon's \"___ and Stimpy\"",
     "stars": 4,
     "category": "wordplay",
     "register": "modern",
     "tags": [
      "sourced"
     ]
    },
    {
     "num": 4,
     "answer": "THE",
     "clue": "Last word of \"Finnegans Wake\"",
     "stars": 4,
     "category": "wordplay",
     "register": "modern",
     "tags": [
      "sourced"
     ]
    },
    {
     "num": 7,
     "answer": "TEA",
     "clue": "Hot gossip, in slang",
     "stars": 3,
     "category": "sports-leisure",
     "tags": [
      "food"
     ]
    },
    {
     "num": 8,
     "answer": "AIR",
     "clue": "Broadcast, as a show",
     "stars": 2,
     "category": "science-nature",
     "tags": [
      "nature"
     ]
    },
    {
     "num": 9,
     "answer": "ELNORTE",
     "clue": "Best Original Screenplay nominee of 1984",
     "stars": 3,
     "category": "wordplay",
     "tags": [
      "sourced"
     ]
    },
    {
     "num": 11,
     "answer": "EAT",
     "clue": "Absorb, as unexpected costs",
     "stars": 2,
     "category": "wordplay",
     "tags": [
      "food"
     ]
    },
    {
     "num": 12,
     "answer": "RATTAIL",
     "clue": "Kind of comb",
     "stars": 3,
     "category": "wordplay",
     "tags": [
      "sourced"
     ]
    },
    {
     "num": 16,
     "answer": "OPT",
     "clue": "Go (for)",
     "stars": 1,
     "category": "wordplay"
    },
    {
     "num": 17,
     "answer": "RAE",
     "clue": "\"Norma ___,\" Field film",
     "stars": 4,
     "category": "entertainment",
     "register": "modern",
     "tags": [
      "sourced"
     ]
    },
    {
     "num": 18,
     "answer": "NEE",
     "clue": "Dolley Madison, ___ Payne",
     "stars": 3,
     "category": "wordplay",
     "tags": [
      "sourced"
     ]
    },
    {
     "num": 19,
     "answer": "ENT",
     "clue": "\"The Lord of the Rings\" creature",
     "stars": 4,
     "category": "wordplay",
     "register": "modern",
     "tags": [
      "sourced"
     ]
    }
   ],
   "down": [
    {
     "num": 1,
     "answer": "RTE",
     "clue": "Mail carrier's daily loop: Abbr.",
     "stars": 3,
     "category": "geography",
     "tags": [
      "travel"
     ]
    },
    {
     "num": 2,
     "answer": "EEL",
     "clue": "Unagi, at a sushi bar",
     "stars": 2,
     "category": "science-nature",
     "tags": [
      "animals",
      "food"
     ]
    },
    {
     "num": 3,
     "answer": "NANETTE",
     "clue": "She was told \"No, no\"",
     "stars": 4,
     "category": "wordplay",
     "register": "modern",
     "tags": [
      "sourced"
     ]
    },
    {
     "num": 4,
     "answer": "TARTARE",
     "clue": "Steak ___ (raw meat dish)",
     "stars": 3,
     "category": "wordplay",
     "tags": [
      "sourced"
     ]
    },
    {
     "num": 5,
     "answer": "HIT",
     "clue": "Single or double, on a scorecard",
     "stars": 2,
     "category": "entertainment",
     "tags": [
      "music",
      "sports"
     ]
    },
    {
     "num": 6,
     "answer": "ERE",
     "clue": "Poet's 'prior to'",
     "stars": 1,
     "category": "arts-literature",
     "tags": [
      "books"
     ]
    },
    {
     "num": 10,
     "answer": "OAT",
     "clue": "Barista's dairy dodge?",
     "stars": 4,
     "category": "science-nature",
     "register": "modern",
     "tags": [
      "food"
     ]
    },
    {
     "num": 12,
     "answer": "RON",
     "clue": "Wood of the Rolling Stones",
     "stars": 3,
     "category": "wordplay",
     "tags": [
      "sourced"
     ]
    },
    {
     "num": 13,
     "answer": "APE",
     "clue": "Mimic",
     "stars": 2,
     "category": "science-nature",
     "tags": [
      "animals"
     ]
    },
    {
     "num": 14,
     "answer": "IAN",
     "clue": "Ziering of \"Beverly Hills 90210\"",
     "stars": 4,
     "category": "wordplay",
     "register": "modern",
     "tags": [
      "sourced"
     ]
    },
    {
     "num": 15,
     "answer": "LET",
     "clue": "Serve that clips the net cord",
     "stars": 3,
     "category": "sports-leisure",
     "tags": [
      "sports"
     ]
    }
   ]
  },
  "weekday": 6
 },
 {
  "id": "lib-mini-w6-3",
  "kind": "mini",
  "title": "No Training Wheels",
  "author": "The Riddle Constructors",
  "difficulty": 6,
  "size": {
   "rows": 7,
   "cols": 7
  },
  "grid": [
   "ART#PBS",
   "HAH#RAH",
   "ITERATE",
   "##ANN##",
   "ATTACHE",
   "TEE#EON",
   "EAR#RED"
  ],
  "clues": {
   "across": [
    {
     "num": 1,
     "answer": "ART",
     "clue": "It may be fine or martial",
     "stars": 3,
     "category": "arts-literature",
     "tags": [
      "art",
      "school"
     ]
    },
    {
     "num": 4,
     "answer": "PBS",
     "clue": "Monogram of the \"Ozymandias\" poet",
     "stars": 4,
     "category": "wordplay",
     "register": "modern",
     "tags": [
      "sourced"
     ]
    },
    {
     "num": 7,
     "answer": "HAH",
     "clue": "\"I told you so!\"",
     "stars": 3,
     "category": "wordplay",
     "register": "modern",
     "tags": [
      "sourced"
     ]
    },
    {
     "num": 8,
     "answer": "RAH",
     "clue": "Rallying cry?",
     "stars": 4,
     "category": "sports-leisure",
     "tags": [
      "sourced"
     ]
    },
    {
     "num": 9,
     "answer": "ITERATE",
     "clue": "Say it one more time",
     "stars": 3,
     "category": "wordplay",
     "tags": [
      "sourced"
     ]
    },
    {
     "num": 11,
     "answer": "ANN",
     "clue": "That girl in \"That Girl\"",
     "stars": 4,
     "category": "wordplay",
     "register": "modern",
     "tags": [
      "sourced"
     ]
    },
    {
     "num": 12,
     "answer": "ATTACHE",
     "clue": "Court case?",
     "stars": 4,
     "category": "wordplay",
     "tags": [
      "sourced"
     ]
    },
    {
     "num": 16,
     "answer": "TEE",
     "clue": "Course requirement?",
     "stars": 4,
     "category": "wordplay",
     "tags": [
      "sourced"
     ]
    },
    {
     "num": 17,
     "answer": "EON",
     "clue": "What a wait at the DMV feels like",
     "stars": 3,
     "category": "science-nature",
     "tags": [
      "time",
      "science"
     ]
    },
    {
     "num": 18,
     "answer": "EAR",
     "clue": "What a natural musician plays by",
     "stars": 3,
     "category": "science-nature",
     "tags": [
      "food",
      "music"
     ]
    },
    {
     "num": 19,
     "answer": "RED",
     "clue": "In the ___ (losing money)",
     "stars": 1,
     "category": "science-nature",
     "tags": [
      "art",
      "valentines"
     ]
    }
   ],
   "down": [
    {
     "num": 1,
     "answer": "AHI",
     "clue": "Kona catch, maybe",
     "stars": 3,
     "category": "wordplay",
     "tags": [
      "sourced"
     ]
    },
    {
     "num": 2,
     "answer": "RAT",
     "clue": "What you smell when double-crossed?",
     "stars": 4,
     "category": "science-nature",
     "tags": [
      "animals"
     ]
    },
    {
     "num": 3,
     "answer": "THEATER",
     "clue": "House that prefers a full house",
     "stars": 4,
     "category": "entertainment",
     "tags": [
      "movies",
      "art"
     ]
    },
    {
     "num": 4,
     "answer": "PRANCER",
     "clue": "\"Now, ___ and Vixen!\"",
     "stars": 4,
     "category": "wordplay",
     "register": "modern",
     "tags": [
      "sourced"
     ]
    },
    {
     "num": 5,
     "answer": "BAT",
     "clue": "Slugger's lumber",
     "stars": 2,
     "category": "science-nature",
     "tags": [
      "animals",
      "sports",
      "halloween"
     ]
    },
    {
     "num": 6,
     "answer": "SHE",
     "clue": "\"___ walks in beauty . . . \": Byron",
     "stars": 4,
     "category": "wordplay",
     "register": "modern",
     "tags": [
      "sourced"
     ]
    },
    {
     "num": 10,
     "answer": "RNA",
     "clue": "Part of a cell nucleus",
     "stars": 3,
     "category": "wordplay",
     "tags": [
      "sourced"
     ]
    },
    {
     "num": 12,
     "answer": "ATE",
     "clue": "Polished off a plate",
     "stars": 2,
     "category": "wordplay",
     "tags": [
      "food"
     ]
    },
    {
     "num": 13,
     "answer": "TEA",
     "clue": "Hot gossip, in slang",
     "stars": 3,
     "category": "sports-leisure",
     "tags": [
      "food"
     ]
    },
    {
     "num": 14,
     "answer": "HOE",
     "clue": "Row maker in the garden",
     "stars": 2,
     "category": "science-nature",
     "tags": [
      "nature",
      "spring"
     ]
    },
    {
     "num": 15,
     "answer": "END",
     "clue": "Gridiron lineman, tight or split",
     "stars": 3,
     "category": "wordplay",
     "tags": [
      "sports",
      "movies"
     ]
    }
   ]
  },
  "weekday": 6
 },
 {
  "id": "lib-mini-w7-1",
  "kind": "mini",
  "title": "Sunday Stroll",
  "author": "The Riddle Constructors",
  "difficulty": 7,
  "size": {
   "rows": 7,
   "cols": 7
  },
  "grid": [
   "EWE#SET",
   "TEN#HAH",
   "ASTAIRE",
   "##EYE##",
   "PANELED",
   "EMT#DNA",
   "ICE#STY"
  ],
  "clues": {
   "across": [
    {
     "num": 1,
     "answer": "EWE",
     "clue": "Flock mother",
     "stars": 2,
     "category": "science-nature",
     "tags": [
      "animals",
      "nature"
     ]
    },
    {
     "num": 4,
     "answer": "SET",
     "clue": "Where a film crew works",
     "stars": 2,
     "category": "entertainment",
     "tags": [
      "movies",
      "sports"
     ]
    },
    {
     "num": 7,
     "answer": "TEN",
     "clue": "Full count of bowling pins",
     "stars": 1,
     "category": "sports-leisure",
     "tags": [
      "sports",
      "olympics"
     ]
    },
    {
     "num": 8,
     "answer": "HAH",
     "clue": "\"I told you so!\"",
     "stars": 3,
     "category": "wordplay",
     "register": "modern",
     "tags": [
      "sourced"
     ]
    },
    {
     "num": 9,
     "answer": "ASTAIRE",
     "clue": "Dancer who \"rates A-1\"?",
     "stars": 5,
     "category": "wordplay",
     "register": "modern",
     "tags": [
      "sourced"
     ]
    },
    {
     "num": 11,
     "answer": "EYE",
     "clue": "Hurricane's calmest spot",
     "stars": 3,
     "category": "science-nature",
     "tags": [
      "science",
      "nature"
     ]
    },
    {
     "num": 12,
     "answer": "PANELED",
     "clue": "Worked on walls",
     "stars": 3,
     "category": "wordplay",
     "tags": [
      "sourced"
     ]
    },
    {
     "num": 16,
     "answer": "EMT",
     "clue": "Siren-riding lifesaver, briefly",
     "stars": 2,
     "category": "science-nature",
     "tags": [
      "science"
     ]
    },
    {
     "num": 17,
     "answer": "DNA",
     "clue": "Crime-lab evidence, for short",
     "stars": 2,
     "category": "science-nature",
     "tags": [
      "science"
     ]
    },
    {
     "num": 18,
     "answer": "ICE",
     "clue": "Seal the win, in sports slang",
     "stars": 3,
     "category": "science-nature",
     "tags": [
      "winter",
      "sports"
     ]
    },
    {
     "num": 19,
     "answer": "STY",
     "clue": "Pork place?",
     "stars": 4,
     "category": "wordplay",
     "tags": [
      "sourced"
     ]
    }
   ],
   "down": [
    {
     "num": 1,
     "answer": "ETA",
     "clue": "Pilot's projection, for short",
     "stars": 2,
     "category": "geography",
     "tags": [
      "travel"
     ]
    },
    {
     "num": 2,
     "answer": "WES",
     "clue": "Unseld of the N.B.A.",
     "stars": 3,
     "category": "wordplay",
     "tags": [
      "sourced"
     ]
    },
    {
     "num": 3,
     "answer": "ENTENTE",
     "clue": "Understanding between nations",
     "stars": 3,
     "category": "wordplay",
     "tags": [
      "sourced"
     ]
    },
    {
     "num": 4,
     "answer": "SHIELDS",
     "clue": "U.S.S. Enterprise defenses",
     "stars": 3,
     "category": "wordplay",
     "tags": [
      "sourced"
     ]
    },
    {
     "num": 5,
     "answer": "EAR",
     "clue": "What a natural musician plays by",
     "stars": 3,
     "category": "science-nature",
     "tags": [
      "food",
      "music"
     ]
    },
    {
     "num": 6,
     "answer": "THE",
     "clue": "\"___ Sun Also Rises\"",
     "stars": 4,
     "category": "wordplay",
     "register": "modern",
     "tags": [
      "sourced"
     ]
    },
    {
     "num": 10,
     "answer": "AYE",
     "clue": "Vote in favor",
     "stars": 1,
     "category": "history",
     "tags": [
      "travel"
     ]
    },
    {
     "num": 12,
     "answer": "PEI",
     "clue": "Louvre Pyramid architect",
     "stars": 3,
     "category": "wordplay",
     "tags": [
      "sourced"
     ]
    },
    {
     "num": 13,
     "answer": "AMC",
     "clue": "\"Breaking Bad\" network",
     "stars": 3,
     "category": "wordplay",
     "register": "modern",
     "tags": [
      "sourced"
     ]
    },
    {
     "num": 14,
     "answer": "ENT",
     "clue": "\"The Lord of the Rings\" creature",
     "stars": 4,
     "category": "wordplay",
     "register": "modern",
     "tags": [
      "sourced"
     ]
    },
    {
     "num": 15,
     "answer": "DAY",
     "clue": "What Rome wasn't built in a single one of",
     "stars": 2,
     "category": "science-nature",
     "tags": [
      "nature"
     ]
    }
   ]
  },
  "weekday": 7
 },
 {
  "id": "lib-mini-w7-2",
  "kind": "mini",
  "title": "The Long Way Home",
  "author": "The Riddle Constructors",
  "difficulty": 7,
  "size": {
   "rows": 7,
   "cols": 7
  },
  "grid": [
   "TET#SPA",
   "AWE#WES",
   "BESEECH",
   "##TEE##",
   "PSALTER",
   "SIT#IDA",
   "ARE#EYE"
  ],
  "clues": {
   "across": [
    {
     "num": 1,
     "answer": "TET",
     "clue": "Offensive time?",
     "stars": 4,
     "category": "wordplay",
     "tags": [
      "sourced"
     ]
    },
    {
     "num": 4,
     "answer": "SPA",
     "clue": "Resort with robes and cucumber water",
     "stars": 2,
     "category": "sports-leisure",
     "tags": [
      "travel"
     ]
    },
    {
     "num": 7,
     "answer": "AWE",
     "clue": "Standard reaction at the Grand Canyon",
     "stars": 3,
     "category": "wordplay",
     "tags": [
      "travel"
     ]
    },
    {
     "num": 8,
     "answer": "WES",
     "clue": "Unseld of the N.B.A.",
     "stars": 3,
     "category": "wordplay",
     "tags": [
      "sourced"
     ]
    },
    {
     "num": 9,
     "answer": "BESEECH",
     "clue": "Beg",
     "stars": 2,
     "category": "wordplay",
     "tags": [
      "sourced"
     ]
    },
    {
     "num": 11,
     "answer": "TEE",
     "clue": "Course requirement?",
     "stars": 4,
     "category": "wordplay",
     "tags": [
      "sourced"
     ]
    },
    {
     "num": 12,
     "answer": "PSALTER",
     "clue": "Book of the Bible",
     "stars": 3,
     "category": "arts-literature",
     "tags": [
      "sourced"
     ]
    },
    {
     "num": 16,
     "answer": "SIT",
     "clue": "Hold still for the portrait painter",
     "stars": 3,
     "category": "wordplay",
     "tags": [
      "animals",
      "household"
     ]
    },
    {
     "num": 17,
     "answer": "IDA",
     "clue": "Gilbert &amp; Sullivan princess",
     "stars": 3,
     "category": "wordplay",
     "tags": [
      "sourced"
     ]
    },
    {
     "num": 18,
     "answer": "ARE",
     "clue": "Exist, for two or more",
     "stars": 2,
     "category": "wordplay"
    },
    {
     "num": 19,
     "answer": "EYE",
     "clue": "It's kept on the ball?",
     "stars": 3,
     "category": "science-nature",
     "tags": [
      "science",
      "nature"
     ]
    }
   ],
   "down": [
    {
     "num": 1,
     "answer": "TAB",
     "clue": "Browser window's neighbor",
     "stars": 2,
     "category": "wordplay",
     "tags": [
      "tech"
     ]
    },
    {
     "num": 2,
     "answer": "EWE",
     "clue": "Flock mother",
     "stars": 2,
     "category": "science-nature",
     "tags": [
      "animals",
      "nature"
     ]
    },
    {
     "num": 3,
     "answer": "TESTATE",
     "clue": "Not unwilling?",
     "stars": 4,
     "category": "wordplay",
     "tags": [
      "sourced"
     ]
    },
    {
     "num": 4,
     "answer": "SWEETIE",
     "clue": "Kind of pie?",
     "stars": 4,
     "category": "wordplay",
     "tags": [
      "sourced"
     ]
    },
    {
     "num": 5,
     "answer": "PEC",
     "clue": "Little muscle?",
     "stars": 4,
     "category": "wordplay",
     "tags": [
      "sourced"
     ]
    },
    {
     "num": 6,
     "answer": "ASH",
     "clue": "Classic baseball-bat wood",
     "stars": 2,
     "category": "science-nature",
     "tags": [
      "nature",
      "sports"
     ]
    },
    {
     "num": 10,
     "answer": "EEL",
     "clue": "Unagi, at a sushi bar",
     "stars": 2,
     "category": "science-nature",
     "tags": [
      "animals",
      "food"
     ]
    },
    {
     "num": 12,
     "answer": "PSA",
     "clue": "\"Don't do drugs!\" ad, e.g., for short",
     "stars": 4,
     "category": "entertainment",
     "register": "modern",
     "tags": [
      "sourced"
     ]
    },
    {
     "num": 13,
     "answer": "SIR",
     "clue": "Respectful reply to the boss",
     "stars": 3,
     "category": "history",
     "tags": [
      "history"
     ]
    },
    {
     "num": 14,
     "answer": "EDY",
     "clue": "Joseph ___, who lent his name to some ice cream",
     "stars": 3,
     "category": "wordplay",
     "tags": [
      "sourced"
     ]
    },
    {
     "num": 15,
     "answer": "RAE",
     "clue": "Charlotte of \"The Facts of Life\"",
     "stars": 4,
     "category": "entertainment",
     "register": "modern",
     "tags": [
      "sourced"
     ]
    }
   ]
  },
  "weekday": 7
 },
 {
  "id": "lib-mini-w7-3",
  "kind": "mini",
  "title": "Lazy Morning",
  "author": "The Riddle Constructors",
  "difficulty": 7,
  "size": {
   "rows": 7,
   "cols": 7
  },
  "grid": [
   "AHI#MOM",
   "SET#ERA",
   "PEERAGE",
   "##RAN##",
   "NEATENS",
   "EMT#SAT",
   "SUE#THY"
  ],
  "clues": {
   "across": [
    {
     "num": 1,
     "answer": "AHI",
     "clue": "Yellowfin tuna, on menus",
     "stars": 3,
     "category": "wordplay",
     "tags": [
      "sourced"
     ]
    },
    {
     "num": 4,
     "answer": "MOM",
     "clue": "Pop idol?",
     "stars": 4,
     "category": "wordplay",
     "tags": [
      "sourced"
     ]
    },
    {
     "num": 7,
     "answer": "SET",
     "clue": "Where a film crew works",
     "stars": 2,
     "category": "entertainment",
     "tags": [
      "movies",
      "sports"
     ]
    },
    {
     "num": 8,
     "answer": "ERA",
     "clue": "Jazz Age or Space Age, e.g.",
     "stars": 2,
     "category": "history",
     "tags": [
      "time",
      "history"
     ]
    },
    {
     "num": 9,
     "answer": "PEERAGE",
     "clue": "Dukes, earls, etc.",
     "stars": 3,
     "category": "wordplay",
     "tags": [
      "sourced"
     ]
    },
    {
     "num": 11,
     "answer": "RAN",
     "clue": "Was a candidate",
     "stars": 3,
     "category": "wordplay",
     "tags": [
      "sourced"
     ]
    },
    {
     "num": 12,
     "answer": "NEATENS",
     "clue": "Puts in order",
     "stars": 3,
     "category": "wordplay",
     "tags": [
      "sourced"
     ]
    },
    {
     "num": 16,
     "answer": "EMT",
     "clue": "Siren-riding lifesaver, briefly",
     "stars": 2,
     "category": "science-nature",
     "tags": [
      "science"
     ]
    },
    {
     "num": 17,
     "answer": "SAT",
     "clue": "Posed for a portrait",
     "stars": 2,
     "category": "arts-literature",
     "tags": [
      "art",
      "school"
     ]
    },
    {
     "num": 18,
     "answer": "SUE",
     "clue": "Good name for a lawyer?",
     "stars": 4,
     "category": "wordplay",
     "tags": [
      "sourced"
     ]
    },
    {
     "num": 19,
     "answer": "THY",
     "clue": "\"Love ___ neighbor ...\"",
     "stars": 4,
     "category": "wordplay",
     "register": "modern",
     "tags": [
      "sourced"
     ]
    }
   ],
   "down": [
    {
     "num": 1,
     "answer": "ASP",
     "clue": "Cleopatra's fatal companion",
     "stars": 2,
     "category": "history",
     "tags": [
      "animals",
      "history"
     ]
    },
    {
     "num": 2,
     "answer": "HEE",
     "clue": "TV's \"___ Haw\"",
     "stars": 4,
     "category": "entertainment",
     "register": "modern",
     "tags": [
      "sourced"
     ]
    },
    {
     "num": 3,
     "answer": "ITERATE",
     "clue": "Remind, in a way",
     "stars": 3,
     "category": "wordplay",
     "tags": [
      "sourced"
     ]
    },
    {
     "num": 4,
     "answer": "MEANEST",
     "clue": "Closest to the Grinch",
     "stars": 3,
     "category": "wordplay",
     "tags": [
      "sourced"
     ]
    },
    {
     "num": 5,
     "answer": "ORG",
     "clue": "Part of some e-mail addresses",
     "stars": 3,
     "category": "wordplay",
     "tags": [
      "sourced"
     ]
    },
    {
     "num": 6,
     "answer": "MAE",
     "clue": "West of \"My Little Chickadee\"",
     "stars": 4,
     "category": "wordplay",
     "register": "modern",
     "tags": [
      "sourced"
     ]
    },
    {
     "num": 10,
     "answer": "RAT",
     "clue": "What you smell when double-crossed?",
     "stars": 4,
     "category": "science-nature",
     "tags": [
      "animals"
     ]
    },
    {
     "num": 12,
     "answer": "NES",
     "clue": "Super ___ (old game console)",
     "stars": 3,
     "category": "sports-leisure",
     "tags": [
      "sourced"
     ]
    },
    {
     "num": 13,
     "answer": "EMU",
     "clue": "Ostrich's Outback cousin",
     "stars": 2,
     "category": "science-nature",
     "tags": [
      "animals"
     ]
    },
    {
     "num": 14,
     "answer": "NAH",
     "clue": "\"I don't think so\"",
     "stars": 3,
     "category": "wordplay",
     "register": "modern",
     "tags": [
      "sourced"
     ]
    },
    {
     "num": 15,
     "answer": "STY",
     "clue": "Pork place?",
     "stars": 4,
     "category": "wordplay",
     "tags": [
      "sourced"
     ]
    }
   ]
  },
  "weekday": 7
 }
]